{
  "version": "0.1",
  "language": "en",
  "words": [
    "datamodel",
    "datasource",
    "deps",
    "healthcheck",
    "logfiles",
    "microservice",
    "microservices",
    "nanos",
    "oneof",
    "proto",
    "protogen",
    "signin",
    "signup",
    "typecheck",
    "upsert",
    "workdir"
  ],
  "ignoreWords": [
    "henken",
    "henkenclub",
    "protolint",
    "plexsystems",
    "bcrpyt",
    "protobuf",
    "streetsidesoftware",
    "nestjs",
    "grpc",
    "hadolint",
    "scripty",
    "arkweid",
    "lefthook",
    "dmmf",
    "protoc",
    "mkdir",
    "mysqladmin",
    "bcrypt",
    "libssl",
    "eslintcache",
    "streetsidesoftware"
  ],
  "ignorePaths": [
    ".vscode/extensions.json",
    "dist/**",
    "node_modules/**",
    "migration/**",
    "scripts/**",
    "src/protogen/**",
    ".cspell.json",
    "package-lock.json"
  ],
  "enableFiletypes": ["dockerfile", "dotenv", "ignore", "proto3"]
}
